{
  "timestamp": "2026-06-11 08:06",
  "checked": 6,
  "new_by_profile": {
    "python-internals": {
      "count": 7,
      "results": [
        {
          "title": "What Is the Python Global Interpreter Lock (GIL)? \u2013 Real Python",
          "url": "https://realpython.com/python-gil/"
        },
        {
          "title": "CPython Internals & Performance: The Ultimate Guide to the Python...",
          "url": "https://www.amazon.com/CPython-Internals-Performance-Interpreter-Optimization/dp/B0FXJFSXCK"
        },
        {
          "title": "How Your Python Code Actually Runs",
          "url": "https://nazquadri.dev/blog/the-layer-below/11-how-code-runs/"
        },
        {
          "title": "How to Implement Basic Multiprocessing with While Loops in Python...",
          "url": "https://www.pythontutorials.net/blog/basic-multiprocessing-with-while-loop/"
        },
        {
          "title": "CPython Internals memory management",
          "url": "https://github.com/zpoint/CPython-Internals/blob/master/Interpreter/memory_management/memory_management.md"
        },
        {
          "title": "Understanding the Python GIL - YouTube",
          "url": "https://www.youtube.com/watch?v=Obt-vMVdM8s"
        },
        {
          "title": "Memory Management | zpoint/CPython-Internals | DeepWiki",
          "url": "https://deepwiki.com/zpoint/CPython-Internals/2-memory-management"
        }
      ]
    },
    "algorithms": {
      "count": 10,
      "results": [
        {
          "title": "Optimization techniques for improving time complexity in algorithms",
          "url": "https://leetcode.com/discuss/study-guide/3221866/Optimization-techniques-for-improving-time-complexity-in-algorithms/"
        },
        {
          "title": "I Tried 20+ Java DSA Courses with LeetCode Exercises on Udemy ...",
          "url": "https://medium.com/javarevisited/i-tried-20-java-dsa-courses-with-leetcode-exercises-on-udemy-here-are-my-top-5-recommendations-86085dfbcd84"
        },
        {
          "title": "Data Structures & Algorithms in Java + 150 Leetcode Problems",
          "url": "https://www.coursera.org/specializations/packt-data-structures-and-algorithms-in-java-150-leetcode-problems"
        },
        {
          "title": "ATU Scholars Symposium: Data Structures & Algorithms Prep Hub",
          "url": "https://orc.library.atu.edu/atu_rs/2026/2026/51/"
        },
        {
          "title": "Essential Starter Techniques to Conquer Coding Challenges - Discuss",
          "url": "https://leetcode.com/discuss/study-guide/5450007/LeetCode-Level-Up:-Essential-Starter-Techniques-to-Conquer-Coding-Challenges/"
        },
        {
          "title": "Leetcode Interviews Fail to Measure Real Engineering Skills",
          "url": "https://www.linkedin.com/posts/sajjaad-khader_dear-tech-companies-its-2026-leetcode-activity-7452355472281460736-JLik"
        },
        {
          "title": "Top 10 Data Structures Courses (2026 Edition) - MentorCruise",
          "url": "https://mentorcruise.com/courses/datastructures/"
        },
        {
          "title": "LeetCode Alternatives 2026: Which Platform Fills the Gap?",
          "url": "https://www.codeintuition.io/blogs/leetcode-alternatives-2026"
        },
        {
          "title": "Leetcode survival guide - DEV Community",
          "url": "https://dev.to/dfs_with_memo/leetcode-survival-guide-1cp3"
        },
        {
          "title": "How to Pass Leetcode Interviews: The Ritual That Works",
          "url": "https://proandroiddev.com/how-to-pass-leetcode-interviews-the-ritual-that-works-a788ff2f4f27"
        }
      ]
    },
    "functional-programming": {
      "count": 10,
      "results": [
        {
          "title": "Idiomatic monads in Rust | varkor's blog",
          "url": "https://varkor.github.io/blog/2019/03/28/idiomatic-monads-in-rust.html"
        },
        {
          "title": "WHAT IS A MONAD? Functional Programming Patterns... - YouTube",
          "url": "https://www.youtube.com/watch?v=8DJtc3zJ5nY"
        },
        {
          "title": "Monads and Monad-Like Patterns in Rust: Exploring Functional...",
          "url": "https://softwarepatternslexicon.com/rust/functional-programming-patterns-in-rust/monads-and-monad-like-patterns-in-rust/"
        },
        {
          "title": "All About Monads - HaskellWiki",
          "url": "https://wiki.haskell.org/All_About_Monads"
        },
        {
          "title": "Monads (and Functors and Applicatives) explained (badly) in Rust",
          "url": "https://users.rust-lang.org/t/monads-and-functors-and-applicatives-explained-badly-in-rust/15187"
        },
        {
          "title": "nsu-syspro/haskell-monads-2026",
          "url": "https://github.com/nsu-syspro/haskell-monads-2026"
        },
        {
          "title": "Monads as a Programming Pattern",
          "url": "https://samgrayson.me/essays/monads-as-a-programming-pattern/"
        },
        {
          "title": "Monads And Their Use in Modern Programming",
          "url": "https://www.linkedin.com/pulse/monads-use-modern-programming-enrique-ortu\u00f1o-znk9f"
        },
        {
          "title": "Haskell Monads \u2014 Monday Morning Haskell",
          "url": "https://mmhaskell.com/monads"
        },
        {
          "title": "Monads in Functional Programming: From Theory to... | Medium",
          "url": "https://medium.com/@mo.mirjavadi/monads-in-functional-programming-from-theory-to-practice-9f9f93c0bf51"
        }
      ]
    },
    "type-systems": {
      "count": 8,
      "results": [
        {
          "title": "Gradual typing - Wikipedia",
          "url": "https://en.wikipedia.org/wiki/Gradual_typing"
        },
        {
          "title": "Elixir v1.20 released: now a gradually typed language",
          "url": "https://elixir-lang.org/blog/2026/06/03/elixir-v1-20-0-released/"
        },
        {
          "title": "Type inference of all constructs and the next 15 months",
          "url": "https://elixir-lang.org/blog/2026/01/09/type-inference-of-all-and-next-15/"
        },
        {
          "title": "From Duck Typing to Strict Types: Python's Evolving Type System",
          "url": "https://leapcell.medium.com/from-duck-typing-to-strict-types-pythons-evolving-type-system-09df4f5205f0"
        },
        {
          "title": "What type systems do you find interesting / useful / underrated?",
          "url": "https://www.reddit.com/r/ProgrammingLanguages/comments/1oj58xg/what_type_systems_do_you_find_interesting_useful/"
        },
        {
          "title": "What is a type system, really? - Lambda Land",
          "url": "https://lambdaland.org/posts/2023-01-17_what_is_a_type_system_really/"
        },
        {
          "title": "TYPE SYSTEMS - The Consensus",
          "url": "https://theconsensus.dev/t/type-systems.html"
        },
        {
          "title": "Efficient Selection of Type Annotations for Performance ... - arXiv",
          "url": "https://arxiv.org/pdf/2603.05649"
        }
      ]
    },
    "compilers": {
      "count": 9,
      "results": [
        {
          "title": "Python JIT Tutorial: How to Enable and Optimize the CPython JIT...",
          "url": "https://www.linkedin.com/pulse/python-jit-tutorial-how-enable-optimize-xslsc"
        },
        {
          "title": "A Deep Dive into Compilers, Interpreters, Bytecode, and JIT...",
          "url": "https://teddyaryono.dev/blog/compiler-interpreter/"
        },
        {
          "title": "LLVM Compiler Optimization",
          "url": "https://iq.opengenus.org/llvm-compiler-optimization/"
        },
        {
          "title": "Interpreters and Compilers \u2014 36-750 Statistical Computing",
          "url": "https://36-750.github.io/concepts/interpreters-compilers/"
        },
        {
          "title": "Modern JavaScript Engines: Key Optimizations, JIT Compilers...",
          "url": "https://www.javaspring.net/blog/what-optimizations-do-modern-javascript-engines-perform/"
        },
        {
          "title": "Computer Programming for Beginners | What are Interpreters...",
          "url": "https://www.youtube.com/watch?v=svJerixawV0"
        },
        {
          "title": "Compiler Design and Interpreters: How... | Computer Science Authority",
          "url": "https://computerscienceauthority.com/compiler-design-and-interpreters"
        },
        {
          "title": "GitHub - codetesla51/how-to-build-a-programming-language...",
          "url": "https://github.com/codetesla51/how-to-build-a-programming-language"
        },
        {
          "title": "Just-in-Time for Runtime Interpretation... | White Knight Labs",
          "url": "https://whiteknightlabs.com/2025/12/23/just-in-time-for-runtime-interpretation-unmasking-the-world-of-llvm-ir-based-jit-execution/"
        }
      ]
    },
    "system-design": {
      "count": 10,
      "results": [
        {
          "title": "7 Proven Scalability Patterns in Distributed Systems | Medium",
          "url": "https://medium.com/@careerwithnadeem/7-proven-scalability-patterns-in-distributed-systems-e09112c2ffdb"
        },
        {
          "title": "# Day 4: Load Balancing in Distributed Systems... - DEV Community",
          "url": "https://dev.to/vikram_kumar_2101/-day-4-load-balancing-in-distributed-systems-a-deep-dive-41d5"
        },
        {
          "title": "Top 30 System Design Interview Questions (2026)",
          "url": "https://www.datainterview.com/blog/system-design-interview-questions"
        },
        {
          "title": "Explaining Distributed Systems Like I'm 5 - YouTube",
          "url": "https://www.youtube.com/watch?v=CESKgdNiKJw"
        },
        {
          "title": "Memcached Python Client: Distributed Caching Patterns 2026",
          "url": "https://johal.in/memcached-python-client-distributed-caching-patterns-2026/"
        },
        {
          "title": "Designing Scalable Video Streaming Systems with Load Balancers...",
          "url": "https://www.linkedin.com/posts/kalph-dev_systemdesign-distributedsystems-aws-activity-7434551783265525762-cNZ0"
        },
        {
          "title": "Design Issues of Distributed System (1).pptx",
          "url": "https://www.slideshare.net/slideshow/design-issues-of-distributed-system-1-pptx/272027019"
        },
        {
          "title": "Caching Patterns: Cache-Aside, Write-Through | knowledgelib.io",
          "url": "https://knowledgelib.io/software/patterns/caching-patterns/2026"
        },
        {
          "title": "Caching Patterns in AWS: Reduce Latency and Improve Performance...",
          "url": "https://knowledge.businesscompassllc.com/caching-patterns-in-aws-reduce-latency-and-improve-performance/"
        },
        {
          "title": "Zonal Gateway Load Balancing in Centralized E/E Architectures...",
          "url": "https://eureka.patsnap.com/blog/scout-report/zonal-gateway-load-balancing-in-centralized-e-e-architectures-latency-redundancy-and-fault-containment/"
        }
      ]
    }
  },
  "total_new": 54
}